{
  "ok": true,
  "url": "https://dash.heleket.com/business/create",
  "merchant_name": "NOWICKI_3",
  "uuid": null,
  "meta_content": null,
  "body": "Предложить идею\n2\n\nСоздать мерчанта\n\nШаг 1 из 2\n\nВыберите тип и добавьте URL проекта\n\nСсылка на ваш сайт или Telegram-бота\n\nНазвание мерчанта\n\nТип\n\nПосле выбора типа проекта, который вы хотите отправить, введите правильный URL-адрес и название проекта.\n\nTelegram бот\nВебсайт\n\nURL-адрес проекта\n\nНазвание проекта\n\nСохранить и выйти\nПродолжить\n\nⒸ 2026 Heleket\n\nPrivacy policy\n\nTerms of use\n\nAML\n\nFAQ\nAPI\nКонтакты",
  "clicks": [
    "Обзор",
    "Обзор",
    "Личный",
    "Бизнес",
    "Карты",
    "Карты",
    "История",
    "История",
    "Предложить идею",
    "2",
    "Шаг 1 из 2",
    "Название мерчанта",
    "Введите название мерчанта",
    "tg_bot",
    "Telegram бот",
    "website",
    "Вебсайт",
    "URL-адрес проекта",
    "Введите URL-адрес веб-сайта",
    "Название проекта",
    "Введите название вашего проекта",
    "Сохранить и выйти",
    "Продолжить",
    "FAQ",
    "API",
    "Контакты",
    "Privacy policy",
    "Terms of use",
    "AML",
    "FAQ",
    "API",
    "Контакты",
    "FAQ",
    "API",
    "Контакты",
    "Обзор",
    "Личный",
    "Бизнес",
    "Карта",
    "История"
  ]
}